tsimpl-0.1.0.dist-info/METADATA
tsimpl-0.1.0.dist-info/WHEEL
tsimpl-0.1.0.dist-info/entry_points.txt
tsimpl-0.1.0.dist-info/licenses/LICENSE
tsimpl/__init__.py
tsimpl/tsimpl.abi3.so
tsimpl-0.1.0.dist-info/RECORD
