Metadata-Version: 2.4
Name: tsimpl
Version: 0.1.0
Classifier: Programming Language :: Python :: 3
Classifier: Programming Language :: Rust
Classifier: License :: OSI Approved :: MIT License
Classifier: Intended Audience :: Science/Research
Classifier: Topic :: Scientific/Engineering
License-File: LICENSE
Summary: E-graph T-count optimizer for Clifford+T (Python bindings)
Keywords: e-graphs,compiler,quantum,clifford+T,optimization
Author-email: Harshit Lakum <harshitlakum2012@gmail.com>
License: MIT
Requires-Python: >=3.9
